pson/__init__.py
pyPSON-2.0.0.dist-info/METADATA
pyPSON-2.0.0.dist-info/WHEEL
pyPSON-2.0.0.dist-info/top_level.txt
pyPSON-2.0.0.dist-info/RECORD
