Metadata-Version: 2.1
Name: pyPSON
Version: 2.0.0
Summary: module for parsing and dumping PSON
Home-page: https://github.com/lechos22/pyPSON
Author: lechos22
Author-email: UNKNOWN
License: BSD 3-Clause License
Platform: UNKNOWN
